{
    "key": "group_67878db05de23",
    "title": "Block - Portfolio blocks",
    "fields": [
        {
            "key": "field_67878db1d02c1",
            "label": "Title",
            "name": "title",
            "aria-label": "",
            "type": "text",
            "instructions": "",
            "required": 0,
            "conditional_logic": 0,
            "wrapper": {
                "width": "",
                "class": "",
                "id": ""
            },
            "wpml_cf_preferences": 0,
            "default_value": "",
            "maxlength": "",
            "allow_in_bindings": 0,
            "placeholder": "",
            "prepend": "",
            "append": ""
        },
        {
            "key": "field_67878e14d02c2",
            "label": "Items",
            "name": "items",
            "aria-label": "",
            "type": "relationship",
            "instructions": "",
            "required": 0,
            "conditional_logic": 0,
            "wrapper": {
                "width": "",
                "class": "",
                "id": ""
            },
            "wpml_cf_preferences": 3,
            "post_type": [
                "portfolio"
            ],
            "post_status": [
                "publish"
            ],
            "taxonomy": "",
            "filters": [
                "search"
            ],
            "return_format": "id",
            "min": "",
            "max": "",
            "allow_in_bindings": 0,
            "elements": "",
            "bidirectional": 0,
            "bidirectional_target": []
        }
    ],
    "location": [
        [
            {
                "param": "block",
                "operator": "==",
                "value": "acf\/portfolio-blocks"
            }
        ]
    ],
    "menu_order": 0,
    "position": "normal",
    "style": "default",
    "label_placement": "top",
    "instruction_placement": "label",
    "hide_on_screen": "",
    "active": true,
    "description": "",
    "show_in_rest": 0,
    "acfml_field_group_mode": "advanced",
    "modified": 1736937014
}
